graddog/__init__.py
graddog/compgraph.py
graddog/functions.py
graddog/math.py
graddog/tools.py
graddog/trace.py
GradDog-1.3.0.dist-info/LICENSE
GradDog-1.3.0.dist-info/METADATA
GradDog-1.3.0.dist-info/WHEEL
GradDog-1.3.0.dist-info/top_level.txt
GradDog-1.3.0.dist-info/RECORD
