Metadata-Version: 2.1
Name: GradDog
Version: 1.3.0
Summary: Perform automatic differentiation (final project CS107)
Home-page: https://github.com/git-fetch-git-roll-over/GradDog.git
Author: Peyton Benac, Max Cembalest, Seeam Shahid Noor, Ivan Shu
Author-email: pbenac@college.harvard.edu
License: MIT
Platform: UNKNOWN
Classifier: Programming Language :: Python :: 3
Classifier: Programming Language :: Python :: 3.7
Requires-Dist: numpy
Requires-Dist: pytest
Requires-Dist: pandas
Requires-Dist: matplotlib
